LICENSE
MANIFEST.in
README.rst
requirements.txt
setup.cfg
setup.py
test_requirements.txt
Flask_Breathalyzer.egg-info/PKG-INFO
Flask_Breathalyzer.egg-info/SOURCES.txt
Flask_Breathalyzer.egg-info/dependency_links.txt
Flask_Breathalyzer.egg-info/requires.txt
Flask_Breathalyzer.egg-info/top_level.txt
flask_breathalyzer/__init__.py
flask_breathalyzer/breathalyzer.py
flask_breathalyzer/utils.py